evaluation/__init__.py
evaluation/src/__init__.py
evaluation/src/evaluation_main.py
evaluation/src/LLMPrompts/__init__.py
evaluation/src/LLMPrompts/_prompts.py
evaluation/src/dataprocessing/__init__.py
evaluation/src/dataprocessing/ragaas_processor.py
evaluation/src/evaluation_metrices/__init__.py
evaluation/src/evaluation_metrices/_alignment_coverage_score.py
evaluation/src/evaluation_metrices/_answer_completeness.py
evaluation/src/evaluation_metrices/_answer_correctness.py
evaluation/src/evaluation_metrices/_answer_factual_correctness.py
evaluation/src/evaluation_metrices/_answer_relevancy.py
evaluation/src/evaluation_metrices/_answer_similarity.py
evaluation/src/evaluation_metrices/_answer_trueness.py
evaluation/src/evaluation_metrices/_qag_method.py
evaluation/src/evaluation_metrices/_rts_method.py
evaluation/src/evaluation_model/__init__.py
evaluation/src/evaluation_model/ragaas_evaluator.py
helper_files/__init__.py
helper_files/_gpt_chat_completion.py
helper_files/helper_gpt_gateway.py
helper_files/logger.py
helper_files/ragaas_constants.py
helper_files/utils.py
helper_files/llm_model_config/__init__.py
helper_files/llm_model_config/_gpt_.py
helper_files/llm_model_config/_huggingface_.py
helper_files/llm_model_config/model_config_loader.py
ragaasfirstmoduletest-0.0.1.dist-info/METADATA
ragaasfirstmoduletest-0.0.1.dist-info/WHEEL
ragaasfirstmoduletest-0.0.1.dist-info/top_level.txt
ragaasfirstmoduletest-0.0.1.dist-info/RECORD
