Metadata-Version: 2.1
Name: ragaasfirstmoduletest
Version: 0.0.1
Summary: My first RAGAAS package and test
Author: Tung Nguyen
Author-email: Xuan.Nguyen@carelon.com
Keywords: python,first package
Classifier: Development Status :: 3 - Alpha
Classifier: Intended Audience :: Education
Classifier: Programming Language :: Python :: 2
Classifier: Programming Language :: Python :: 3
Classifier: Operating System :: MacOS :: MacOS X
Classifier: Operating System :: Microsoft :: Windows
Requires-Dist: deepeval
Requires-Dist: ragas
